LICENSE
README.md
setup.py
tcpkissserver/__init__.py
tcpkissserver/server.py
tcpkissserver.egg-info/PKG-INFO
tcpkissserver.egg-info/SOURCES.txt
tcpkissserver.egg-info/dependency_links.txt
tcpkissserver.egg-info/top_level.txt